{"target":"Crypt::SSLeay","name":"Crypt::SSLeay","dist":"Crypt-SSLeay-0.72","provides":{"Crypt::SSLeay::Err":{"file":"lib/Crypt/SSLeay/Err.pm"},"Crypt::SSLeay::Version":{"file":"lib/Crypt/SSLeay/Version.pm"},"Crypt::SSLeay::Conn":{"file":"lib/Crypt/SSLeay/Conn.pm"},"Net::SSL":{"file":"lib/Net/SSL.pm","version":"2.86"},"Crypt::SSLeay::X509":{"file":"lib/Crypt/SSLeay/X509.pm"},"Crypt::SSLeay::CTX":{"file":"lib/Crypt/SSLeay/CTX.pm"},"Crypt::SSLeay":{"file":"SSLeay.pm","version":"0.72"},"Crypt::SSLeay::MainContext":{"file":"lib/Crypt/SSLeay/MainContext.pm"}},"version":"0.72","pathname":"N/NA/NANIS/Crypt-SSLeay-0.72.tar.gz"}